classic_caesar.py
classic_caesar-1.0.0.dist-info/WHEEL
classic_caesar-1.0.0.dist-info/METADATA
classic_caesar-1.0.0.dist-info/RECORD
