Metadata-Version: 2.1
Name: classic-caesar
Version: 1.0.0
Summary: Модуль для зашифровывания файлов. | File encryption module.
Author: F_social
Requires-Python: >=3.8,<4.0
Classifier: Programming Language :: Python :: 3
Classifier: Programming Language :: Python :: 3.8
Classifier: Programming Language :: Python :: 3.9
